euclidean_hausdorff/__init__.py
euclidean_hausdorff/eucl_haus.py
euclidean_hausdorff/main.py
euclidean_hausdorff/point_cloud.py
euclidean_hausdorff/transformation.py
euclidean_hausdorff-1.3.1.dist-info/METADATA
euclidean_hausdorff-1.3.1.dist-info/WHEEL
euclidean_hausdorff-1.3.1.dist-info/licenses/LICENSE
euclidean_hausdorff-1.3.1.dist-info/RECORD
