Metadata-Version: 2.3
Name: euclidean_hausdorff
Version: 1.3.1
Dynamic: Requires-Dist
Summary: quick approximation of the Gromov–Hausdorff distance restricted to Euclidean isometries
Project-URL: Homepage, https://github.com/bcecil2/euclidean_hausdorff
Project-URL: Issues, https://github.com/bcecil2/euclidean_hausdorff/issues
Author: Blake Cecil
Author-email: Vladyslav Oles <vlad.oles@proton.me>
License: The MIT License (MIT)
License-File: LICENSE
Classifier: License :: OSI Approved :: MIT License
Classifier: Operating System :: OS Independent
Classifier: Programming Language :: Python :: 3
Requires-Python: >=3.9
